{
  "generatedAt": "2026-06-24 10:24 KST",
  "target": "KOSPI forward 20 trading-day maximum drawdown",
  "sampleCount": 112,
  "overall": {
    "count": 112,
    "avgForwardMaxDrawdownPct": -4.67,
    "worstForwardMaxDrawdownPct": -19.24,
    "hitRateDrawdownOver5Pct": 39.3
  },
  "byBucket": {
    "관심": {
      "count": 34,
      "avgForwardMaxDrawdownPct": -2.04,
      "worstForwardMaxDrawdownPct": -16.28,
      "hitRateDrawdownOver5Pct": 14.7
    },
    "주의": {
      "count": 63,
      "avgForwardMaxDrawdownPct": -6.2,
      "worstForwardMaxDrawdownPct": -19.24,
      "hitRateDrawdownOver5Pct": 52.4
    },
    "경고": {
      "count": 15,
      "avgForwardMaxDrawdownPct": -4.2,
      "worstForwardMaxDrawdownPct": -10.45,
      "hitRateDrawdownOver5Pct": 40.0
    }
  },
  "recentSamples": [
    {
      "date": "2026-05-21",
      "score": 66.7,
      "bucket": "주의",
      "forwardMaxDrawdownPct": -4.24
    },
    {
      "date": "2026-05-22",
      "score": 65.1,
      "bucket": "주의",
      "forwardMaxDrawdownPct": -4.63
    },
    {
      "date": "2026-05-26",
      "score": 62.4,
      "bucket": "주의",
      "forwardMaxDrawdownPct": -7.0
    },
    {
      "date": "2026-05-27",
      "score": 62.8,
      "bucket": "주의",
      "forwardMaxDrawdownPct": -9.05
    },
    {
      "date": "2026-05-28",
      "score": 62.6,
      "bucket": "주의",
      "forwardMaxDrawdownPct": -8.56
    },
    {
      "date": "2026-05-29",
      "score": 61.7,
      "bucket": "주의",
      "forwardMaxDrawdownPct": -11.7
    },
    {
      "date": "2026-06-01",
      "score": 64.7,
      "bucket": "주의",
      "forwardMaxDrawdownPct": -14.84
    },
    {
      "date": "2026-06-02",
      "score": 62.6,
      "bucket": "주의",
      "forwardMaxDrawdownPct": -14.96
    },
    {
      "date": "2026-06-04",
      "score": 68.7,
      "bucket": "주의",
      "forwardMaxDrawdownPct": -13.37
    },
    {
      "date": "2026-06-05",
      "score": 75.8,
      "bucket": "경고",
      "forwardMaxDrawdownPct": -8.29
    },
    {
      "date": "2026-06-08",
      "score": 77.6,
      "bucket": "경고",
      "forwardMaxDrawdownPct": 0.0
    },
    {
      "date": "2026-06-09",
      "score": 76.2,
      "bucket": "경고",
      "forwardMaxDrawdownPct": -4.52
    },
    {
      "date": "2026-06-10",
      "score": 77.9,
      "bucket": "경고",
      "forwardMaxDrawdownPct": 0.0
    },
    {
      "date": "2026-06-11",
      "score": 75.1,
      "bucket": "경고",
      "forwardMaxDrawdownPct": 0.0
    },
    {
      "date": "2026-06-12",
      "score": 71.8,
      "bucket": "주의",
      "forwardMaxDrawdownPct": 0.0
    },
    {
      "date": "2026-06-15",
      "score": 66.8,
      "bucket": "주의",
      "forwardMaxDrawdownPct": -1.54
    },
    {
      "date": "2026-06-16",
      "score": 65.2,
      "bucket": "주의",
      "forwardMaxDrawdownPct": -3.58
    },
    {
      "date": "2026-06-17",
      "score": 66.7,
      "bucket": "주의",
      "forwardMaxDrawdownPct": -5.08
    },
    {
      "date": "2026-06-18",
      "score": 60.8,
      "bucket": "주의",
      "forwardMaxDrawdownPct": -7.17
    },
    {
      "date": "2026-06-22",
      "score": 60.6,
      "bucket": "주의",
      "forwardMaxDrawdownPct": -7.69
    }
  ],
  "notes": [
    "This is a lightweight rolling diagnostic, not a full historical validation.",
    "Scores use the current model over the recent dashboard timeseries window."
  ]
}
