{
  "generatedAt": "2026-07-07 16:10:20 KST",
  "source": "Yahoo Finance and Naver Finance chart endpoints",
  "yahooSymbols": {
    "kospi": {
      "symbol": "^KS11",
      "label": "KOSPI",
      "lastDate": "2026-07-07",
      "lastClose": 7656.3101,
      "observations": 485
    },
    "kosdaq": {
      "symbol": "^KQ11",
      "label": "KOSDAQ",
      "lastDate": "2026-07-07",
      "lastClose": 831.23,
      "observations": 485
    },
    "usdkrw": {
      "symbol": "KRW=X",
      "label": "USD/KRW",
      "lastDate": "2026-07-07",
      "lastClose": 1528.02,
      "observations": 517
    },
    "vix": {
      "symbol": "^VIX",
      "label": "VIX",
      "lastDate": "2026-07-06",
      "lastClose": 15.57,
      "observations": 501
    },
    "us10y": {
      "symbol": "^TNX",
      "label": "US 10Y",
      "lastDate": "2026-07-02",
      "lastClose": 4.485,
      "observations": 499
    },
    "kodex200": {
      "symbol": "069500.KS",
      "label": "KODEX 200",
      "lastDate": "2026-07-07",
      "lastClose": 123710.0,
      "observations": 482
    },
    "kodex_leverage": {
      "symbol": "122630.KS",
      "label": "KODEX Leverage",
      "lastDate": "2026-07-07",
      "lastClose": 158895.0,
      "observations": 482
    },
    "sox": {
      "symbol": "^SOX",
      "label": "Philadelphia Semiconductor Index",
      "lastDate": "2026-07-06",
      "lastClose": 12900.1396,
      "observations": 500
    },
    "nvda": {
      "symbol": "NVDA",
      "label": "NVIDIA",
      "lastDate": "2026-07-06",
      "lastClose": 195.55,
      "observations": 500
    },
    "tsm": {
      "symbol": "TSM",
      "label": "TSMC ADR",
      "lastDate": "2026-07-06",
      "lastClose": 451.79,
      "observations": 500
    },
    "avgo": {
      "symbol": "AVGO",
      "label": "Broadcom",
      "lastDate": "2026-07-06",
      "lastClose": 373.9,
      "observations": 500
    },
    "amd": {
      "symbol": "AMD",
      "label": "AMD",
      "lastDate": "2026-07-06",
      "lastClose": 552.05,
      "observations": 500
    },
    "mu": {
      "symbol": "MU",
      "label": "Micron",
      "lastDate": "2026-07-06",
      "lastClose": 984.75,
      "observations": 500
    },
    "asml": {
      "symbol": "ASML",
      "label": "ASML ADR",
      "lastDate": "2026-07-06",
      "lastClose": 1825.0699,
      "observations": 500
    },
    "aapl": {
      "symbol": "AAPL",
      "label": "Apple",
      "lastDate": "2026-07-06",
      "lastClose": 312.66,
      "observations": 500
    },
    "msft": {
      "symbol": "MSFT",
      "label": "Microsoft",
      "lastDate": "2026-07-06",
      "lastClose": 386.74,
      "observations": 500
    },
    "googl": {
      "symbol": "GOOGL",
      "label": "Alphabet",
      "lastDate": "2026-07-06",
      "lastClose": 366.46,
      "observations": 500
    },
    "meta": {
      "symbol": "META",
      "label": "Meta Platforms",
      "lastDate": "2026-07-06",
      "lastClose": 600.29,
      "observations": 500
    },
    "amzn": {
      "symbol": "AMZN",
      "label": "Amazon",
      "lastDate": "2026-07-06",
      "lastClose": 244.16,
      "observations": 500
    },
    "samsung": {
      "symbol": "005930.KS",
      "label": "Samsung Electronics",
      "lastDate": "2026-07-07",
      "lastClose": 296000.0,
      "observations": 484
    },
    "hynix": {
      "symbol": "000660.KS",
      "label": "SK hynix",
      "lastDate": "2026-07-07",
      "lastClose": 2201000.0,
      "observations": 484
    },
    "hanmi": {
      "symbol": "042700.KS",
      "label": "Hanmi Semiconductor",
      "lastDate": "2026-07-07",
      "lastClose": 210500.0,
      "observations": 484
    },
    "dbhitek": {
      "symbol": "000990.KS",
      "label": "DB HiTek",
      "lastDate": "2026-07-07",
      "lastClose": 111800.0,
      "observations": 484
    },
    "leeno": {
      "symbol": "058470.KQ",
      "label": "Leeno Industrial",
      "lastDate": "2026-07-07",
      "lastClose": 71900.0,
      "observations": 484
    },
    "hyg": {
      "symbol": "HYG",
      "label": "iShares High Yield Corporate Bond ETF",
      "lastDate": "2026-07-06",
      "lastClose": 79.87,
      "observations": 500
    },
    "lqd": {
      "symbol": "LQD",
      "label": "iShares Investment Grade Corporate Bond ETF",
      "lastDate": "2026-07-06",
      "lastClose": 108.67,
      "observations": 500
    },
    "eem": {
      "symbol": "EEM",
      "label": "iShares MSCI Emerging Markets ETF",
      "lastDate": "2026-07-06",
      "lastClose": 67.57,
      "observations": 500
    }
  },
  "naverSymbols": {
    "samsung": {
      "symbol": "005930",
      "label": "Samsung Electronics",
      "lastDate": "2026-07-07",
      "lastClose": 296000.0,
      "lastVolume": 31975948,
      "lastForeignOwnership": 46.69,
      "observations": 506
    },
    "hynix": {
      "symbol": "000660",
      "label": "SK hynix",
      "lastDate": "2026-07-07",
      "lastClose": 2201000.0,
      "lastVolume": 6013581,
      "lastForeignOwnership": 50.17,
      "observations": 506
    },
    "hanmi": {
      "symbol": "042700",
      "label": "Hanmi Semiconductor",
      "lastDate": "2026-07-07",
      "lastClose": 210500.0,
      "lastVolume": 573842,
      "lastForeignOwnership": 7.47,
      "observations": 506
    },
    "dbhitek": {
      "symbol": "000990",
      "label": "DB HiTek",
      "lastDate": "2026-07-07",
      "lastClose": 111800.0,
      "lastVolume": 588401,
      "lastForeignOwnership": 27.98,
      "observations": 506
    },
    "leeno": {
      "symbol": "058470",
      "label": "Leeno Industrial",
      "lastDate": "2026-07-07",
      "lastClose": 71900.0,
      "lastVolume": 821431,
      "lastForeignOwnership": 31.45,
      "observations": 506
    },
    "kodex200": {
      "symbol": "069500",
      "label": "KODEX 200",
      "lastDate": "2026-07-07",
      "lastClose": 123710.0,
      "lastVolume": 21892579,
      "lastForeignOwnership": 23.38,
      "observations": 506
    },
    "kodex_leverage": {
      "symbol": "122630",
      "label": "KODEX Leverage",
      "lastDate": "2026-07-07",
      "lastClose": 158895.0,
      "lastVolume": 16349492,
      "lastForeignOwnership": 0.2,
      "observations": 506
    }
  },
  "groupScores": [
    {
      "id": "ai_semi",
      "label": "AI Semi",
      "score": 72.3,
      "weight": 0.26,
      "contribution": 18.79,
      "indicatorCount": 3
    },
    {
      "id": "crash",
      "label": "Crash Stress",
      "score": 92.8,
      "weight": 0.18,
      "contribution": 16.71,
      "indicatorCount": 2
    },
    {
      "id": "macro",
      "label": "Macro",
      "score": 49.5,
      "weight": 0.3,
      "contribution": 14.85,
      "indicatorCount": 4
    },
    {
      "id": "overheating",
      "label": "Overheating",
      "score": 79.7,
      "weight": 0.09,
      "contribution": 7.17,
      "indicatorCount": 2
    },
    {
      "id": "flow",
      "label": "Flow",
      "score": 65.3,
      "weight": 0.1,
      "contribution": 6.53,
      "indicatorCount": 1
    },
    {
      "id": "liquidity",
      "label": "Liquidity",
      "score": 23.4,
      "weight": 0.07,
      "contribution": 1.64,
      "indicatorCount": 1
    }
  ],
  "indicators": [
    {
      "id": "kospi_price_stress",
      "name": "KOSPI 가격 스트레스",
      "category": "한국주식",
      "group": "crash",
      "value": 93.1,
      "unit": "score",
      "weight": 0.11,
      "trend": "up",
      "detail": "KOSPI 7,656.31, 20일 수익률 -5.44%, 20일 변동성 +69.15%, 고점대비 -16.00%",
      "source": "Yahoo Finance chart: ^KS11",
      "contribution": 10.24,
      "contributionPct": 11.0
    },
    {
      "id": "kosdaq_growth_stress",
      "name": "KOSDAQ 성장주 스트레스",
      "category": "한국주식",
      "group": "crash",
      "value": 92.4,
      "unit": "score",
      "weight": 0.07,
      "trend": "flat",
      "detail": "KOSDAQ 831.23, 20일 수익률 -14.11%, 20일 변동성 +57.68%",
      "source": "Yahoo Finance chart: ^KQ11",
      "contribution": 6.47,
      "contributionPct": 7.0
    },
    {
      "id": "usdkrw_fx_pressure",
      "name": "원/달러 환율 압력",
      "category": "외환",
      "group": "macro",
      "value": 63.8,
      "unit": "score",
      "weight": 0.1,
      "trend": "down",
      "detail": "USD/KRW 1,528.02, 20일 변화율 -0.06%, 2년 분위 96.2",
      "source": "Yahoo Finance chart: KRW=X",
      "contribution": 6.38,
      "contributionPct": 10.0
    },
    {
      "id": "global_volatility_pressure",
      "name": "글로벌 변동성 압력",
      "category": "변동성",
      "group": "macro",
      "value": 32.8,
      "unit": "score",
      "weight": 0.08,
      "trend": "flat",
      "detail": "VIX 15.57, 20일 변화율 +1.10%, 2년 분위 22.8",
      "source": "Yahoo Finance chart: ^VIX",
      "contribution": 2.62,
      "contributionPct": 8.0
    },
    {
      "id": "rates_pressure",
      "name": "글로벌 금리 압력",
      "category": "금리",
      "group": "macro",
      "value": 62.7,
      "unit": "score",
      "weight": 0.07,
      "trend": "down",
      "detail": "미 10년 금리 proxy 4.49, 20일 변화율 -0.13%, 2년 분위 87.0",
      "source": "Yahoo Finance chart: ^TNX",
      "contribution": 4.39,
      "contributionPct": 7.0
    },
    {
      "id": "global_ai_semiconductor_stress",
      "name": "글로벌 AI 반도체 스트레스",
      "category": "AI 반도체",
      "group": "ai_semi",
      "value": 80.8,
      "unit": "score",
      "weight": 0.1,
      "trend": "down",
      "detail": "7개 글로벌 AI 반도체 basket, SOX 12,900.14, SOX 20일 수익률 -5.27%, NVDA 점수 84.7, TSM 점수 78.2",
      "source": "Yahoo Finance chart: ^SOX, NVDA, TSM, AVGO, AMD, MU, ASML",
      "contribution": 8.08,
      "contributionPct": 10.0
    },
    {
      "id": "bigtech_ai_demand_pressure",
      "name": "빅테크 AI 수요 우려",
      "category": "AI 수요",
      "group": "ai_semi",
      "value": 60.1,
      "unit": "score",
      "weight": 0.06,
      "trend": "flat",
      "detail": "Apple 312.66, Apple 20일 수익률 +0.46%, 빅테크 바스켓 -3.77%, 메모리 공급자 바스켓 +9.70%, 비용압력 격차 +13.47%",
      "source": "Yahoo Finance chart: AAPL, MSFT, GOOGL, META, AMZN, 005930.KS, 000660.KS, MU",
      "contribution": 3.61,
      "contributionPct": 6.0
    },
    {
      "id": "korea_ai_semiconductor_concentration",
      "name": "한국 AI 반도체 쏠림/스트레스",
      "category": "AI 반도체",
      "group": "ai_semi",
      "value": 71.0,
      "unit": "score",
      "weight": 0.1,
      "trend": "flat",
      "detail": "5개 한국 반도체 basket, 삼성전자 296,000.00, SK하이닉스 2,201,000.00, 반도체 60일 상대성과 -8.63%, 쏠림점수 28.8",
      "source": "Yahoo Finance chart: 005930.KS, 000660.KS, 042700.KS, 000990.KS, 058470.KQ, ^KS11",
      "contribution": 7.1,
      "contributionPct": 10.0
    },
    {
      "id": "foreign_ownership_pressure",
      "name": "외국인 소진율 이탈 압력",
      "category": "수급",
      "group": "flow",
      "value": 65.3,
      "unit": "score",
      "weight": 0.1,
      "trend": "up",
      "detail": "대형 메모리 2개사·수급 민감 장비주 한미반도체의 외국인소진율 20일 %p 변화 기준, 최대 이탈폭 0.99%p",
      "source": "Naver Finance chart: 005930, 000660, 042700",
      "contribution": 6.53,
      "contributionPct": 10.0
    },
    {
      "id": "trading_activity_heat",
      "name": "거래량 과열/위축 압력",
      "category": "유동성",
      "group": "liquidity",
      "value": 23.4,
      "unit": "score",
      "weight": 0.07,
      "trend": "flat",
      "detail": "주요 반도체·KODEX ETF 거래량의 60일 평균 대비 평균 괴리 -7.12%, 최대 괴리 +12.27%",
      "source": "Naver Finance chart: 005930, 000660, 042700, 069500, 122630",
      "contribution": 1.64,
      "contributionPct": 7.0
    },
    {
      "id": "single_name_semiconductor_leverage",
      "name": "삼성전자·하이닉스 단일종목 레버리지",
      "category": "단일종목/레버리지",
      "group": "overheating",
      "value": 69.4,
      "unit": "score",
      "weight": 0.04,
      "trend": "up",
      "detail": "삼성전자 296,000.00, SK하이닉스 2,201,000.00, 20일 수익률 삼성 -8.07%·하이닉스 -0.63%, KOSPI 대비 변동성 배율 삼성 1.39x·하이닉스 1.62x",
      "source": "Yahoo Finance chart: 005930.KS, 000660.KS, ^KS11",
      "contribution": 2.78,
      "contributionPct": 4.0
    },
    {
      "id": "global_credit_proxy_stress",
      "name": "글로벌 신용스프레드 proxy",
      "category": "신용/크레딧",
      "group": "macro",
      "value": 29.3,
      "unit": "score",
      "weight": 0.05,
      "trend": "up",
      "detail": "HYG/LQD 상대가격 기준, 20일 수익률 +0.22%, 고점대비 -1.01%",
      "source": "Yahoo Finance chart: HYG, LQD",
      "contribution": 1.46,
      "contributionPct": 5.0
    },
    {
      "id": "emerging_market_stress",
      "name": "신흥국 위험선호 스트레스",
      "category": "글로벌",
      "group": "overheating",
      "value": 87.9,
      "unit": "score",
      "weight": 0.05,
      "trend": "up",
      "detail": "EEM 67.57, 20일 수익률 -2.21%, 고점대비 -5.11%",
      "source": "Yahoo Finance chart: EEM",
      "contribution": 4.39,
      "contributionPct": 5.0
    }
  ]
}
